{
  "gravity" : [
    0.0, -9.8
  ],

  "player" : [
    250.0, 75.0
  ],

  "levelObjects" : [
    {
      "type" : "CUBE",
      "position" : [
        100.0, 175.0
      ]
    },
    {
      "type" : "CUBE",
      "position" : [
        200.0, 75.0
      ]
    },
    {
      "type" : "CUBE",
      "position" : [
        200.0, 100.0
      ]
    },{
      "type" : "CUBE",
      "position" : [
        200.0, 125.0
      ]
    },{
      "type" : "CUBE",
      "position" : [
        200.0, 150.0
      ]
    },
    {
      "type" : "BUTTON",
      "position" : [
        75.0, 50.0
      ]
    }
  ],

  "finish" : [
    950.0, 63.0
  ],

  "walls" : [
    {
      "origin" : [
        0.0, 35.0
      ],
      "end" : [
        977.0, 0.0
      ],
      "floor" : true,
      "portable" : true
    },
    {
      "origin" : [
        40.0, 35.0
      ],
      "end" : [
        0.0, 520.0
      ],
      "floor" : false,
      "portable" : true
    },
    {
      "origin" : [
        925.0, 555.0
      ],
      "end" : [
        0.0, -465.0
      ],
      "floor" : false,
      "portable" : true
    },
    {
      "origin" : [
        925.0, 90.0
      ],
      "end" : [
        52.0, 0.0
      ],
      "floor" : false,
      "portable" : true
    },
    {
      "origin" : [
        0.0, 510.0
      ],
      "end" : [
        977.0, 0.0
      ],
      "floor" : false,
      "portable" : true
    },
    {
      "origin" : [
        270.0, 35.0
      ],
      "end" : [
        0.0, 250.0
      ],
      "floor" : false,
      "portable" : true
    },
    {
      "origin" : [
        270.0, 285.0
      ],
      "end" : [
        415.0, 0.0
      ],
      "floor" : true,
      "portable" : true
    },
    {
      "origin" : [
        685.0, 35.0
      ],
      "end" : [
        0.0, 250.0
      ],
      "floor" : false,
      "portable" : true
    }
  ]
}
